pyxtrace/__init__.py
pyxtrace/__main__.py
pyxtrace/bytecode.py
pyxtrace/cli.py
pyxtrace/core.py
pyxtrace/kernelspy.py
pyxtrace/memory.py
pyxtrace/replay.py
pyxtrace/visual.py
pyxtrace/syscalls/__init__.py
pyxtrace/syscalls/base.py
pyxtrace/syscalls/darwin.py
pyxtrace/syscalls/dummy.py
pyxtrace/syscalls/linux.py
pyxtrace/syscalls/windows.py
pyxtrace-1.2.0.dist-info/licenses/LICENSE
pyxtrace-1.2.0.dist-info/METADATA
pyxtrace-1.2.0.dist-info/WHEEL
pyxtrace-1.2.0.dist-info/entry_points.txt
pyxtrace-1.2.0.dist-info/top_level.txt
pyxtrace-1.2.0.dist-info/RECORD
