Metadata-Version: 2.4
Name: pyxtrace
Version: 1.2.0
Summary: 🩺  Your Python program under the microscope – byte-code, memory & optional syscalls, with a live Streamlit dashboard.
Author-email: Abhineet Saha <abhineet@example.com>
License: MIT License
Classifier: Development Status :: 4 - Beta
Classifier: Intended Audience :: Developers
Classifier: Intended Audience :: Education
Classifier: License :: OSI Approved :: MIT License
Classifier: Programming Language :: Python :: 3
Classifier: Programming Language :: Python :: 3 :: Only
Classifier: Programming Language :: Python :: 3.8
Classifier: Programming Language :: Python :: 3.9
Classifier: Programming Language :: Python :: 3.10
Classifier: Programming Language :: Python :: 3.11
Classifier: Programming Language :: Python :: 3.12
Classifier: Topic :: Software Development :: Debuggers
Classifier: Topic :: System :: Monitoring
Classifier: Topic :: Utilities
Requires-Python: >=3.8
License-File: LICENSE
Requires-Dist: rich>=13.0
Requires-Dist: typer>=0.9
Requires-Dist: streamlit>=1.25
Requires-Dist: plotly>=5.22
Provides-Extra: dev
Requires-Dist: black; extra == "dev"
Requires-Dist: ruff; extra == "dev"
Requires-Dist: mypy; extra == "dev"
Requires-Dist: pytest>=7; extra == "dev"
Requires-Dist: pre-commit; extra == "dev"
Requires-Dist: types-psutil; extra == "dev"
Dynamic: license-file
